MANIFEST.in
readme.md
setup.py
example/__init__.py
example/__main__.py
example/main.1.py
example/main.5.py
example/main.py
example/setup.py
robusdk/__init__.py
robusdk/__main__.py
robusdk/awaitable.py
robusdk/coroutine.py
robusdk/logger.py
robusdk/main.py
robusdk/parser.py
robusdk/sequence.py
robusdk/setup.py
robusdk/stream.py
robusdk.egg-info/PKG-INFO
robusdk.egg-info/SOURCES.txt
robusdk.egg-info/dependency_links.txt
robusdk.egg-info/requires.txt
robusdk.egg-info/top_level.txt
robusdk/ksy/__init__.py
robusdk/ksy/amr_seer_src2k/__init__.py
robusdk/ksy/amr_seer_src2k/rpc/__init__.py
robusdk/ksy/amr_seer_src2k/rpc/method.py
robusdk/ksy/amr_seer_src2k/service/__init__.py
robusdk/ksy/amr_seer_src2k/service/defination.py
robusdk/ksy/amr_seer_src2k/service/pipeline.py
robusdk/ksy/amr_seer_src2k/service/rpc.py
robusdk/ksy/amr_seer_src2k/service/serial.py
robusdk/ksy/cobot_elibot_cs/__init__.py
robusdk/ksy/cobot_elibot_cs/pipeline/MESSAGE_TYPE_ROBOT_HMC.py
robusdk/ksy/cobot_elibot_cs/pipeline/MESSAGE_TYPE_ROBOT_STATE.py
robusdk/ksy/cobot_elibot_cs/pipeline/ROBOT_STATE_PACKAGE_TYPE_ADDITIONAL_INFO.py
robusdk/ksy/cobot_elibot_cs/pipeline/ROBOT_STATE_PACKAGE_TYPE_CARTESIAN_INFO.py
robusdk/ksy/cobot_elibot_cs/pipeline/ROBOT_STATE_PACKAGE_TYPE_CONFIGURATION_DATA.py
robusdk/ksy/cobot_elibot_cs/pipeline/ROBOT_STATE_PACKAGE_TYPE_JOINT_DATA.py
robusdk/ksy/cobot_elibot_cs/pipeline/ROBOT_STATE_PACKAGE_TYPE_MASTERBOARD_DATA.py
robusdk/ksy/cobot_elibot_cs/pipeline/ROBOT_STATE_PACKAGE_TYPE_PRODUCTION_MODE.py
robusdk/ksy/cobot_elibot_cs/pipeline/ROBOT_STATE_PACKAGE_TYPE_PRODUCTION_MODE_DATA.py
robusdk/ksy/cobot_elibot_cs/pipeline/ROBOT_STATE_PACKAGE_TYPE_ROBOT_MODE_DATA.py
robusdk/ksy/cobot_elibot_cs/pipeline/ROBOT_STATE_PACKAGE_TYPE_SAFETY_STATE.py
robusdk/ksy/cobot_elibot_cs/pipeline/ROBOT_STATE_PACKAGE_TYPE_TOOL_COMM_INFO.py
robusdk/ksy/cobot_elibot_cs/pipeline/ROBOT_STATE_PACKAGE_TYPE_TOOL_DATA.py
robusdk/ksy/cobot_elibot_cs/pipeline/__init__.py
robusdk/ksy/cobot_elibot_cs/rpc/__init__.py
robusdk/ksy/cobot_elibot_cs/rpc/atan.py
robusdk/ksy/cobot_elibot_cs/rpc/ceil.py
robusdk/ksy/cobot_elibot_cs/rpc/get_standard_digital_in.py
