Metadata-Version: 2.1
Name: robusdk
Version: 0.4.6
